{
    "stage": {
        "radius": 7000,
        "spawnRadius": 5000
    },
    "npe": [
        {
            "spawner": true,
            "type": {
                "name": "rock"
            },
            "x": 0,
            "y": 0,
            "size": 30,
            "sides": 9,
            "mass": 300,
            "count": 600,
            "radius": 3200,
            "spread": 2800
        },
        {
            "spawner": true,
            "type": {
                "name": "rock"
            },
            "x": 0,
            "y": 0,
            "size": 90,
            "sides": 13,
            "mass": 1000,
            "count": 150,
            "radius": 4200,
            "minRadius": 3000,
            "spread": 2800
        },
        {
            "spawner": true,
            "type": {
                "name": "prize"
            },
            "x": 0,
            "y": 0,
            "radius": 2200,
            "delay": 64,
            "maxPrizes": 30
        },
        {
            "type": {
                "name": "ship"
            },
            "model": "football",
            "name": "Welcome to Sol Wars!",
            "x": 0,
            "y": 0,
            "vx": 0,
            "vy": 0,
            "control": 8,
            "bullet": 0,
            "health": 99999,
            "regen": 99999,
            "color": "#ffffff",
            "decals": [
                {
                    "name": "decal0",
                    "color": "#ffff00"
                },
                {
                    "name": "decal1",
                    "color": "#ffaa11"
                }
            ]
        }
    ]
}
